cypher8/__init__.py
cypher8/package_data.dat
cypher8-1.2.0.data/data/my_data/data_file
cypher8-1.2.0.dist-info/DESCRIPTION.rst
cypher8-1.2.0.dist-info/METADATA
cypher8-1.2.0.dist-info/RECORD
cypher8-1.2.0.dist-info/WHEEL
cypher8-1.2.0.dist-info/entry_points.txt
cypher8-1.2.0.dist-info/metadata.json
cypher8-1.2.0.dist-info/top_level.txt
